scionpathml/__init__.py
scionpathml/Data/__init__.py
scionpathml/Data/Archive/__init__.py
scionpathml/Data/Currently/__init__.py
scionpathml/Data/History/__init__.py
scionpathml/Data/History/Bandwidth/__init__.py
scionpathml/Data/History/Comparer/__init__.py
scionpathml/Data/History/MP-Bandwidth/__init__.py
scionpathml/Data/History/MP-Prober/__init__.py
scionpathml/Data/History/Prober/__init__.py
scionpathml/Data/History/Showpaths/__init__.py
scionpathml/Data/History/Traceroute/__init__.py
scionpathml/Data/Logs/__init__.py
scionpathml/Data/Logs/Bandwidth/__init__.py
scionpathml/Data/Logs/Comparer/__init__.py
scionpathml/Data/Logs/MP-Bandwidth/__init__.py
scionpathml/Data/Logs/MP-Prober/__init__.py
scionpathml/Data/Logs/Prober/__init__.py
scionpathml/Data/Logs/Showpaths/__init__.py
scionpathml/Data/Logs/Traceroute/__init__.py
scionpathml/cli_tools/__init__.py
scionpathml/cli_tools/cli_utils.py
scionpathml/cli_tools/command_manager.py
scionpathml/cli_tools/config_help.py
scionpathml/cli_tools/config_manager.py
scionpathml/cli_tools/cron_manager.py
scionpathml/cli_tools/data_commands.py
scionpathml/cli_tools/data_manager.py
scionpathml/cli_tools/help_manager.py
scionpathml/cli_tools/log_commands.py
scionpathml/cli_tools/log_display.py
scionpathml/cli_tools/log_manager.py
scionpathml/cli_tools/path_utils.py
scionpathml/cli_tools/scionpathml.py
scionpathml/cli_tools/transform_commands.py
scionpathml/cli_tools/transform_manager.py
scionpathml/collector/__init__.py
scionpathml/collector/bandwidth.py
scionpathml/collector/comparer.py
scionpathml/collector/config.py
scionpathml/collector/mp-bandwidth.py
scionpathml/collector/mp-prober.py
scionpathml/collector/pathdiscovery.py
scionpathml/collector/prober.py
scionpathml/collector/traceroute.py
scionpathml/runner/__init__.py
scionpathml/runner/pipeline.sh
scionpathml/transformers/__init__.py
scionpathml/transformers/mp_parse_json_to_csv.py
scionpathml/transformers/parse_json_to_csv.py
scionpathml-1.0.8.dist-info/licenses/LICENSE
scionpathml-1.0.8.dist-info/METADATA
scionpathml-1.0.8.dist-info/WHEEL
scionpathml-1.0.8.dist-info/entry_points.txt
scionpathml-1.0.8.dist-info/top_level.txt
scionpathml-1.0.8.dist-info/RECORD
